{
    "CHOI":"खेल",
    "NHAN_THUONG":"बोनस",
    "BAN_BE":"दोस्त",
    "NHIEM_VU":"उद्देश्य",
    "NANG_CAP":"उन्नत करना",
    "CUA_HANG":"दुकान",
    "CAI_DAT":"सेटिंग",
    "CHON_NGON_NGU":"भाषा चुने",
    "CHON_SAN":"एक एक्सचेंज चुनें",
    "XOA_TAI_KHOAN":"खाता हटा दो",
    "THEM_BAN":"दोस्त जोड़ें",
    "XAC_NHAN":"पुष्टि करना ",
    "THAM_GIA":"जोड़ना ",
    "DA_THAM_GIA":"शामिल",
    "QUAY_LAI_NGAY_MAI":"कल वापस",
    "DA_XAC_NHAN":"की पुष्टि की",
    "FOLLOW_GROUP":"हमारे समूह का अनुसरण करें",
    "THAM_GIA_KENH_TELE":"हमारे टेलीग्राम चैनल से जुड़ें",
    "FOLLOW_TK_CUA_CHUNG_TOI":"हमारे एक्स खाते का अनुसरण करें",
    "FOLLOW_TREN_DISCORD":"डिस्कॉर्ड पर हमें फ़ॉलो करें",
    "FOLLOW_TREN_FACEBOOK":"फेसबुक पर हमें का पालन करें",
    "DANG_KI_KENH_YOUTOBE":"हमारे यूट्यूब चैनल पर सब्सक्राइब करें",
    "MOI_3_NGUOI_BAN":"3 मित्रों को आमंत्रित करें",
    "BAN_MUON_XOA_TK":"क्या आप इस खाते को हटाने के लिए सुनिश्चित हैं?",
    "CONTENT_XOA_TK":"गेम की प्रगति, उपलब्धियों और खरीदारी सहित आपका सारा डेटा स्थायी रूप से हटा दिया जाएगा। इस कार्रवाई को पूर्ववत नहीं किया जा सकता है।",
    "THONG_TIN_THEM_TREN_KENH":"आधिकारिक चैनलों पर अधिक जानकारी",
    "NHIEM_VU_HANG_NGAY":"दैनिक खोज",
    "DUA_TOP":"शीर्ष पर दौड़",
    "DANG_XUAT_TITLE":"लॉग आउट",
    "DANG_XUAT_CONTEN":"क्या आप वाकई अपने खाते से साइन आउट करना चाहते हैं?",
    "KHONG_DU_COIN":"आपके पास पर्याप्त सिक्के नहीं हैं। और प्राप्त करें",
    "NHAN":"प्राप्त करें",
    "DAY":"दिन",
    "CAP_DO":"स्तर",
    "DONG_Y":"सहमत होना",
    "HUY_BO":"रद्द करना",
    "LEN_CAP":"ऊपर का स्तर",
    "SUNG":"बंदूक",
    "TOI_DA":"अधिकतम",
    "EVENT_LOGIN_DA_NHAN_THUONG_CONTENT":"आपको आज अपना इनाम मिला, कृपया कल वापस आएँ।",
    "EVENT_LOGIN_DA_NHAN_THUONG_BUTTON":"कल फिर आना।",
    "DANG_TAN_CONG_PET":"पालतू पशु की उपस्थिति, कृपया प्रतीक्षा करें...",
    "HET_DAN":"तुम्हारे पास बारूद ख़त्म हो गया है।",
    "THIEU_DAN":"तुम्हारे पास पर्याप्त गोलियाँ नहीं हैं।",
    "LOGIN_ERROR_1":"लॉगिन खाता नाम रिक्त नहीं हो सकता।",
    "LOGIN_ERROR_2":"न्यूनतम खाता लंबाई 6 अक्षर है।",
    "LOGIN_ERROR_3":"अधिकतम खाते की लंबाई 20 अक्षर है।",
    "TANG_SO_COIN_NHAN_MOI_LAN_BAN":"। प्रति शॉट प्राप्त सिक्कों की संख्या बढ़ जाती है: ",
    "TANG_SO_DAN_TIEU_HAO_MOI_LAN_BAN":"। प्रति शॉट खपत की गई गोलियों की संख्या बढ़ जाती है: ",
    "SO_COIN_NHAN_MOI_LAN_BAN":". प्रति शॉट प्राप्त सिक्कों की संख्या: ",
    "SO_DAN_TIEU_HAO_MOI_LAN_BAN":"। प्रति शॉट खाई गई गोलियों की संख्या: ",
    "GIAM_TY_LE_BAN_TRUOT":"। चूकने की दर में कमी: ",
    "TY_LE_BAN_TRUNG":"। हिट दर: ",
    "TY_LE_BAO_KICH":"। हमले की दर: ",
    "TY_LE_LIEN_KICH":"। हिट दर: ",
    "TY_LE_JACKPOT":"। जैकपॉट ऑड्स: ",
    "DA_DAT_LEVEL_TOI_DA":"अधिकतम स्तर तक पहुंच गया।",
    "DANG_TAI_DU_LIEU":"डेटा लोड हो रहा है",
    "CHIA_KHOA_DA_NHAN":"कुंजी प्राप्त हुई।",
    "NO_CONNECT_SERVER":"सर्वर से कनेक्ट करने में असमर्थ, कृपया अपना नेटवर्क कनेक्शन जांचें। दोबारा लॉग इन करने के लिए ओके पर क्लिक करें",
    "KIEM_THEM_TIEN":"अधिक पैसे कमाएँ",
    "KHAM_PHA_TRO_CHOI":"गेम एक्सप्लोर करें और पुरस्कार पाएं",
    "TRO_CHOI_GIA_MAT":"और गेम जल्द ही आ रहे हैं",
    "DOI_COIN_LAY_TOKEN":"एसकेपी टोकन के लिए एक्सचेंज एसकेसी सिक्का",
    "GIAO_DICH_TOKEN_TREN_SAN":"एक्सचेंज पर टोकन का व्यापार करें और लाभ कमाएं",
    "PHAN_THUONG_HANG_NGAY":"दैनिक पुरस्कार",
    "NOTE_TICH_LUY_DANG_NHAP":"बिना स्किप किए रोजाना गेम में बारूद जमा करें। रिसीव बटन को रोजाना दबाना होगा",
    "DANG_NHAP_HANG_NGAY":"दैनिक लॉग इन करें",
    "CONTENT_TITLE_BAN_BE":"आपको और आपके दोस्तों को पुरस्कार मिलेगा",
    "MOI_BAN":"आपका स्वागत है",
    "MOI_BAN_PRO":"आपको टेलीग्राम प्रीमियम के लिए आमंत्रित करें",
    "CHO_BAN_VA_BAN_BAN":"आपके और आपके दोस्तों के लिए",
    "LIST_FRIEND":"मित्र सूची",
    "BANG_XEP_HANG":"रैंकिंग",
    "TG_TIEU_COIN":"सिक्के खर्च करो",
    "TG_TIEU_DAN":"गोलियाँ",
    "TG_NHAN_COIN":"सिक्के प्राप्त करें",
    "TG_NHAN_DAN":"गोलियाँ प्राप्त करें",
    "TG_DAN":"बुलेट",
    "TG_BAO_KICH":"हिंसा",
    "TG_LIEN_KICH":"संयुक्त हड़ताल",
    "TG_JACKPOT":"जैकपॉट",
    "TG_COIN":"सिक्के",
    "TG_TOTAL_HIT":"शॉट्स की संख्या",
    "TG_HIT":"हिट की संख्या",
    "TG_MISS":"चूकों की संख्या",
    "TG_FRIEND":"दोस्त",
    "DAN":"बुलेट",
    "GIO":"टोकरी",
    "SO_DAN_MUA_MOI_NGAY":"दिन भर में खरीदी गई गोलियों की मात्रा",
    "NOTE_CONVERT_COIN":"सिक्कों को टोकन में बदलें (एसकेपी)",
    "NOTE_DU_KIEN_PHAT_HANH":"बीएनबी पर नियोजित टोकन जारी करना",
    "NOTE_KHAM_PHA":"गेम एक्सप्लोर करें और पुरस्कार पाएं",
    "NOTE_SAP_RA_MAT":"और गेम जल्द ही आ रहे हैं",
    "NHAP_MA":"यहाँ कोड दर्ज करें",
    "SAO_CHEP_MA":"कोड कॉपी करें",
    "CONTENT_GAMECOMING":"कंटेंट_गेमकमिंग कंटेंट_गेमकमिंग कंटेंट_गेमकमिंग कंटेंट_गेमकमिंग कंटेंट_गेमकमिंग कंटेंट_गेमकमिंग",
    "DOI_COIN_SANG_USDT":"USDT/BNB प्राप्त करने के लिए SKC कॉइन का आदान-प्रदान करें",
    "DUA_TOP_NHAN_THUONG":"पुरस्कार प्राप्त करने के लिए शीर्ष दौड़ में भाग लें",
    "DEM_NGUOC":"उलटी गिनती: ",
    "KET_THUC_SAU":"के बाद समाप्त होता है:",
    "SU_KIEN_DA_KET_THUC":"कार्यक्रम समाप्त हो गया है!",
    "GIO_MAIN":"घंटा",
    "PHUT_MAIN":"मिनट",
    "GIAY_MAIN":"दूसरा",
    "LIEN_KET_VI":"वॉलेट लिंक",
    "THONG_BAO_DELETE_ACCOUNT":"क्या आप इस खाते को हटाने के लिए सुनिश्चित हैं?",
    "SAP_DIEN_RA":"जल्द आ रहा है",
    "DA_KET_THUC":"खत्म",
    "DUATOP_TIEU_COIN":"सिक्के खर्च करो",
    "DUATOP_TIEU_DAN":"बुलेट लक्ष्य",
    "DUATOP_NHAN_COIN":"सिक्के प्राप्त करें",
    "DUATOP_NHAN_DAN":"गोलियाँ प्राप्त करें",
    "DUATOP_DAN":"गोलियाँ",
    "DUATOP_BAO_KICH":"हिंसा",
    "DUATOP_LIEN_KICH":"लिंक स्ट्राइक",
    "DUATOP_JACKPOT":"जैकपॉट",
    "DUATOP_COIN":"सिक्का",
    "DUATOP_TOTAL_HIT":"हिट की कुल संख्या",
    "DUATOP_HIT":"मार",
    "DUATOP_MISS":"याद",
    "DUATOP_FRIEND":"दोस्त",
    "THONG_BAO_DUA_TOP_SAP_DIEN_RA":"शीर्ष रेसिंग इवेंट जल्द ही आ रहा है, उपहार प्राप्त करने के लिए स्काईफार्म से जुड़ें!",
    "THONG_BAO_DUA_TOP_BAT_DAU":"टॉप रेसिंग इवेंट शुरू हो गया है, उपहार प्राप्त करने के लिए स्काईफार्म से जुड़ें!",
    "THONG_BAO_DUA_TOP_DANG_DIEN_RA":"टॉप रेसिंग इवेंट शुरू हो गया है, उपहार प्राप्त करने के लिए स्काईफार्म से जुड़ें!",
    "NHAN_THUONG_DUA_TOP":"शीर्ष पर दौड़ के लिए पुरस्कार प्राप्त करें",
    "QUA_THUONG_DUA_TOP":"शीर्ष रैंकिंग रेसिंग पुरस्कार",
    "CONNECT_WALLET":"वॉलेट कनेक्ट",
    "EVENT_LOGIN_CHUA_NHAN_THUONG_CONTENT":"बिना स्किप किए हर दिन गेम में लॉग इन करके बारूद जमा करें। हर दिन बटन जरूर दबाएं।",
    "CAI_DAT_AM_THANH":"ध्वनि सेटिंग्स"
    }